myrtle/__init__.py
myrtle/bench.py
myrtle/config.py
myrtle/config.toml
myrtle/demo.py
myrtle/logging_setup.py
myrtle/agents/__init__.py
myrtle/agents/base_agent.py
myrtle/agents/fnc_buckettree_ziptie_one_step.py
myrtle/agents/fnc_one_step_curiosity.py
myrtle/agents/fnc_ziptie_one_step.py
myrtle/agents/greedy_state_blind.py
myrtle/agents/greedy_state_blind_eps.py
myrtle/agents/q_learning_buckettree_ziptie.py
myrtle/agents/q_learning_curiosity.py
myrtle/agents/q_learning_eps.py
myrtle/agents/q_learning_ziptie_curiosity.py
myrtle/agents/random_multi_action.py
myrtle/agents/value_avg_curiosity.py
myrtle/demos/__init__.py
myrtle/demos/pendulum.py
myrtle/monitors/__init__.py
myrtle/monitors/bench.html
myrtle/monitors/bench.js
myrtle/monitors/config.js
myrtle/monitors/drawingTools.js
myrtle/monitors/num.js
myrtle/monitors/pendulum.html
myrtle/monitors/pendulum.js
myrtle/monitors/server.py
myrtle/reports/__init__.py
myrtle/reports/buckettree.py
myrtle/reports/fnc.py
myrtle/reports/report_config.py
myrtle/reports/reward.py
myrtle/reports/timing.py
myrtle/reports/ziptie.py
myrtle/tests/__init__.py
myrtle/tests/base_agent_test.py
myrtle/tests/base_world_test.py
myrtle/tests/bench_test.py
myrtle/tests/config_test.py
myrtle/tests/contextual_bandit_test.py
myrtle/tests/fixtures.py
myrtle/tests/greedy_state_blind_agent_test.py
myrtle/tests/greedy_state_blind_eps_agent_test.py
myrtle/tests/integration_test_suite.py
myrtle/tests/intermittent_reward_bandit_world_test.py
myrtle/tests/monitor_server_test.py
myrtle/tests/nonstationary_bandit_world_test.py
myrtle/tests/one_hot_contextual_bandit_test.py
myrtle/tests/pendulum_discrete_world_test.py
myrtle/tests/pendulum_world_test.py
myrtle/tests/q_learning_curiosity_agent_test.py
myrtle/tests/q_learning_eps_agent_test.py
myrtle/tests/random_multi_action_agent_test.py
myrtle/tests/stationary_bandit_world_test.py
myrtle/tests/value_avg_curiosity_test.py
myrtle/tests/world_mocks.py
myrtle/worlds/__init__.py
myrtle/worlds/base_world.py
myrtle-1.0.11.dist-info/METADATA
myrtle-1.0.11.dist-info/WHEEL
myrtle-1.0.11.dist-info/entry_points.txt
myrtle-1.0.11.dist-info/licenses/LICENSE
myrtle-1.0.11.dist-info/RECORD
