Metadata-Version: 2.4
Name: myrtle
Version: 1.0.11
Summary: A workbench and benchmarking framework for real-time reinforcement learning with multiple intermittent rewards
Project-URL: Homepage, https://codeberg.org/brohrer/myrtle
Project-URL: Documentation, https://codeberg.org/brohrer/myrtle/src/branch/main/README.md
Project-URL: Repository, https://codeberg.org/brohrer/myrtle.git
Author-email: Brandon Rohrer <brohrer@gmail.com>
License-File: LICENSE
Classifier: License :: OSI Approved :: MIT License
Classifier: Operating System :: OS Independent
Classifier: Programming Language :: Python :: 3
Requires-Python: >=3.12
Requires-Dist: bucket-tree==0.1.4
Requires-Dist: dsmq==1.4.1
Requires-Dist: matplotlib>=3.10.1
Requires-Dist: naive-cartographer==3.0.1
Requires-Dist: numba>=0.61.2
Requires-Dist: numpy>=2.1.3
Requires-Dist: pacemaker-lite==0.1.3
Requires-Dist: requests>=2.32.3
Requires-Dist: sqlite-logging==0.0.4
Requires-Dist: ziptie==1.2.1
